restbl-0.1.1.dist-info/METADATA
restbl-0.1.1.dist-info/WHEEL
restbl/__init__.py
restbl/restbl.cpython-310-powerpc64le-linux-gnu.so
restbl-0.1.1.dist-info/RECORD
