Metadata-Version: 2.1
Name: restbl
Version: 0.1.1
Classifier: Operating System :: OS Independent
Classifier: Development Status :: 4 - Beta
Classifier: Programming Language :: Rust
Classifier: Programming Language :: Python :: Implementation :: CPython
Classifier: Programming Language :: Python :: Implementation :: PyPy
Summary: Tears of the Kingdom RSTB/RESTBL parser and editing library
Home-Page: https://github.com/NiceneNerd/restbl-py/
Author: Caleb Smith <c.smith@tuta.io>
Author-email: Caleb Smith <c.smith@tuta.io>
License: GPL-3.0-or-later
Requires-Python: >=3.7
Project-URL: Source Code, https://github.com/NiceneNerd/restbl-py/
